tipico_server/__init__.py
tipico_server/__version__.py
tipico_server/conf/tipico_server.conf
tipico_server/instrument_controller/__init__.py
tipico_server/instrument_controller/abstract_instrument.py
tipico_server/instrument_controller/instrument_controller.py
tipico_server/instrument_controller/runner.py
tipico_server/instrument_controller/simulated_instrument.py
tipico_server/instrument_controller/tipico_run_instrument_controller.py
tipico_server/process_monitor/__init__.py
tipico_server/process_monitor/runner.py
tipico_server/process_monitor/tipico_run_process_monitor.py
tipico_server/scripts/__init__.py
tipico_server/scripts/tipico_instrument_controller_1.py
tipico_server/scripts/tipico_instrument_controller_2.py
tipico_server/scripts/tipico_kill_processes.py
tipico_server/scripts/tipico_process_monitor.py
tipico_server/scripts/tipico_stop.py
tipico_server/utils/__init__.py
tipico_server/utils/constants.py
tipico_server/utils/process_startup_helper.py
tipico_server/utils/starter_script_creator.py
tipico_server-0.15.0.dist-info/DESCRIPTION.rst
tipico_server-0.15.0.dist-info/METADATA
tipico_server-0.15.0.dist-info/RECORD
tipico_server-0.15.0.dist-info/WHEEL
tipico_server-0.15.0.dist-info/entry_points.txt
tipico_server-0.15.0.dist-info/metadata.json
tipico_server-0.15.0.dist-info/top_level.txt
