Metadata-Version: 2.0
Name: tipico-server
Version: 0.15.0
Summary: useless controller of a simulated device with PLICO
Home-page: https://github.com/lbusoni/tipico_server
Author: Lorenzo Busoni
Author-email: lorenzo.busoni@inaf.it
License: MIT
Keywords: laboratory,instrumentation control
Platform: UNKNOWN
Classifier: Development Status :: 4 - Beta
Classifier: Operating System :: POSIX :: Linux
Classifier: Programming Language :: Python :: 2.7
Classifier: Programming Language :: Python :: 3
Requires-Dist: plico (>=0.15)
Requires-Dist: tipico (>=0.15)
Requires-Dist: numpy
Requires-Dist: ipython
Requires-Dist: matplotlib
Requires-Dist: scipy
Requires-Dist: psutil
Requires-Dist: configparser
Requires-Dist: six
Requires-Dist: appdirs
Requires-Dist: pyfits
Requires-Dist: futures
